autonomous/__init__.py
autonomous/core/__init__.py
autonomous/core/mcts/__init__.py
autonomous/core/mcts/autonomous_agent.py
autonomous/core/mcts/entity/__init__.py
autonomous/core/mcts/entity/evaluation_model.py
autonomous/core/mcts/entity/node_model.py
autonomous/core/mcts/entity/state_model.py
autonomous/core/mcts/entity/strategy_model.py
autonomous/core/mcts/prompts/__init__.py
autonomous/core/mcts/prompts/ask_human_prompts.py
autonomous/core/mcts/prompts/evaluation_prompts.py
autonomous/core/mcts/prompts/execution_prompts.py
autonomous/core/mcts/prompts/expand_prompts.py
autonomous/core/mcts/prompts/human_feedback_prompts.py
autonomous/core/mcts/prompts/human_input_process_prompt.py
autonomous/core/mcts/prompts/intermediate_prompts.py
autonomous/core/mcts/prompts/interface/__init__.py
autonomous/core/mcts/prompts/interface/prompt_template_interface.py
autonomous/core/mcts/serializer/__init__.py
autonomous/core/mcts/serializer/checnpointer_serializer.py
autonomous/core/mcts/service/__init__.py
autonomous/core/mcts/service/ask_human_service.py
autonomous/core/mcts/service/evaluation_service.py
autonomous/core/mcts/service/execution_service.py
autonomous/core/mcts/service/expand_service.py
autonomous/core/mcts/service/human_feedback_service.py
autonomous/core/mcts/service/human_input_process_service.py
autonomous/core/mcts/workflow/__init__.py
autonomous/core/mcts/workflow/mcts_workflows.py
autonomous/infra/__init__.py
autonomous/infra/parsers.py
autonomous/infra/settings.py
autonomous/infra/llm/__init__.py
autonomous/infra/llm/llms.py
autonomous_agent-0.0.1.dist-info/METADATA
autonomous_agent-0.0.1.dist-info/WHEEL
autonomous_agent-0.0.1.dist-info/top_level.txt
autonomous_agent-0.0.1.dist-info/RECORD
